{
    "id": 26609,
    "name": "Wave 1 (LEGACY)",
    "author": "yopp",
    "creators": ["yopp"],
    "verifier": "yopp",
    "verification": "https://www.youtube.com/watch?v=ZuASPUXUn1w",
    "percentToQualify": "100",
    "password": "",
    "records": [
                {
            "user": "yopp",
            "percent": 100
        },
        {
            "user": "clydie",
            "percent": 100
        },
        {
            "user": "biohazard",
            "percent": 100
        }
    ]
}